sweetbean/__init__.py
sweetbean/_const.py
sweetbean/block.py
sweetbean/data.py
sweetbean/experiment.py
sweetbean/extension/TouchButton.py
sweetbean/extension/__init__.py
sweetbean/llm_utils/__init__.py
sweetbean/llm_utils/prompts.py
sweetbean/stimulus/Choice.py
sweetbean/stimulus/Foraging.py
sweetbean/stimulus/Gabor.py
sweetbean/stimulus/Generic.py
sweetbean/stimulus/HtmlKeyboardResponse.py
sweetbean/stimulus/Image.py
sweetbean/stimulus/RO.py
sweetbean/stimulus/RSVP.py
sweetbean/stimulus/Stimulus.py
sweetbean/stimulus/Survey.py
sweetbean/stimulus/Symbol.py
sweetbean/stimulus/Video.py
sweetbean/stimulus/_Template_.py
sweetbean/stimulus/__init__.py
sweetbean/util/__init__.py
sweetbean/util/data_process.py
sweetbean/util/io.py
sweetbean/util/parse.py
sweetbean/variable/__init__.py
sweetbean-1.3.17.dist-info/licenses/LICENSE
sweetbean-1.3.17.dist-info/METADATA
sweetbean-1.3.17.dist-info/WHEEL
sweetbean-1.3.17.dist-info/top_level.txt
sweetbean-1.3.17.dist-info/RECORD
