Metadata-Version: 2.4
Name: sweetbean
Version: 1.3.17
Summary: A declarative language in python for creating jsPsych experiments
Author-email: Younes Strittmatter <ystrittm@gmail.com>
License: MIT License
Project-URL: homepage, https://github.com/AutoResearch/sweetbean
Project-URL: repository, https://https://github.com/AutoResearch/sweetbeant
Project-URL: documentation, https://autoresearch.github.io/sweetbean/
Requires-Python: <4,>=3.9
License-File: LICENSE
Requires-Dist: jinja2==3.1.4
Requires-Dist: Transcrypt==3.9.3
Requires-Dist: pyppeteer==2.0.0
Requires-Dist: pillow==11.0.0
Provides-Extra: dev
Requires-Dist: sweetbean[test]; extra == "dev"
Requires-Dist: sweetbean[build]; extra == "dev"
Requires-Dist: sweetbean[notebook]; extra == "dev"
Requires-Dist: sweetbean[docs]; extra == "dev"
Provides-Extra: docs
Requires-Dist: mkdocs-material; extra == "docs"
Requires-Dist: mkdocs-gen-files; extra == "docs"
Requires-Dist: mkdocs-literate-nav; extra == "docs"
Requires-Dist: mkdocs-section-index; extra == "docs"
Requires-Dist: mkdocs-multirepo-plugin; extra == "docs"
Requires-Dist: mkdocs-macros-plugin; extra == "docs"
Requires-Dist: mkdocstrings-python; extra == "docs"
Requires-Dist: mkdocs-jupyter; extra == "docs"
Requires-Dist: pymdown-extensions; extra == "docs"
Requires-Dist: notebook; extra == "docs"
Requires-Dist: jupyter; extra == "docs"
Requires-Dist: jupyterlab; extra == "docs"
Provides-Extra: test
Requires-Dist: pytest; extra == "test"
Dynamic: license-file
